cli/__init__.py
cli/cust_measures.py
cli/findings_export.py
cli/findings_sync.py
cli/housekeeper.py
cli/loc.py
cli/measures_export.py
cli/options.py
cli/projects_cli.py
cli/projects_export.py
cli/projects_import.py
cli/rules_cli.py
cli/sonar_tools.py
cli/support.py
migration/README.md
migration/__init__.py
migration/build.sh
migration/deploy.sh
migration/migration.py
migration/pyproject.toml
migration/release.Dockerfile
migration/snapshot.Dockerfile
migration/sonar_migration
migration/what-is-new.md
sonar/__init__.py
sonar/aggregations.py
sonar/api/2025.1.json
sonar/api/9.9.json
sonar/api/__init__.py
sonar/api/cloud.json
sonar/api/manager.py
sonar/app_branches.py
sonar/applications.py
sonar/audit/__init__.py
sonar/audit/problem.py
sonar/audit/rules.json
sonar/audit/rules.py
sonar/audit/severities.py
sonar/audit/types.py
sonar/branches.py
sonar/changelog.py
sonar/cli/__init__.py
sonar/cli/audit.py
sonar/cli/config.py
sonar/cli/maturity.py
sonar/cli/misra.py
sonar/cli/sonar-audit.properties
sonar/cli/sonar-config.schema.json
sonar/cli/sonar-config.schema.yaml
sonar/cli/sonar-maturity.properties
sonar/components.py
sonar/config.json
sonar/config.py
sonar/custom_measures.py
sonar/dce/__init__.py
sonar/dce/app_nodes.py
sonar/dce/nodes.py
sonar/dce/search_nodes.py
sonar/devops.py
sonar/errcodes.py
sonar/exceptions.py
sonar/findings.py
sonar/groups.py
sonar/hotspots.py
sonar/issues.py
sonar/languages.py
sonar/logging.py
sonar/measures.py
sonar/metrics.py
sonar/organizations.py
sonar/permissions/__init__.py
sonar/permissions/aggregation_permissions.py
sonar/permissions/application_permissions.py
sonar/permissions/global_permissions.py
sonar/permissions/permission_templates.py
sonar/permissions/permissions.py
sonar/permissions/portfolio_permissions.py
sonar/permissions/project_permissions.py
sonar/permissions/quality_permissions.py
sonar/permissions/qualitygate_permissions.py
sonar/permissions/qualityprofile_permissions.py
sonar/permissions/template_permissions.py
sonar_tools-3.18.1.dist-info/METADATA
sonar_tools-3.18.1.dist-info/WHEEL
sonar_tools-3.18.1.dist-info/entry_points.txt
sonar_tools-3.18.1.dist-info/licenses/LICENSE
sonar_tools-3.18.1.dist-info/RECORD
