Metadata-Version: 2.4
Name: sonar-tools
Version: 3.18.1
Summary: A collection of utility tools for the SonarQube ecosystem
License-Expression: LGPL-3.0-only
License-File: LICENSE
Keywords: sonarqube,sonar,tools,administration,automation
Author: Olivier Korach
Author-email: olivier.korach@gmail.com
Maintainer: Olivier Korach
Maintainer-email: olivier.korach@gmail.com
Requires-Python: >= 3.9
Classifier: Development Status :: 5 - Production/Stable
Classifier: Intended Audience :: Developers
Classifier: Topic :: Software Development :: Quality Assurance
Classifier: Programming Language :: Python :: 3
Classifier: Programming Language :: Python :: 3.8
Classifier: Programming Language :: Python :: 3.9
Classifier: Programming Language :: Python :: 3.10
Classifier: Programming Language :: Python :: 3.11
Classifier: Programming Language :: Python :: 3.12
Classifier: Programming Language :: Python :: 3.13
Requires-Dist: PyYAML (>=6.0.2)
Requires-Dist: argparse
Requires-Dist: datetime
Requires-Dist: jprops (>=2.0.2)
Requires-Dist: jsonschema (>=4.25.1)
Requires-Dist: levenshtein (>=0.27.1)
Requires-Dist: python-dateutil (>=2.9.0)
Requires-Dist: requests (>=2.32)
Requires-Dist: termgraph (>=0.7.5)
Project-URL: Changelog, https://github.com/okorach/sonar-tools/blob/master/doc/what-is-new.md
Project-URL: Documentation, https://github.com/okorach/sonar-tools/README.md
Project-URL: Homepage, https://pypi.org/sonar-tools
Project-URL: Issues, https://github.com/okorach/sonar-tools/issues
Project-URL: Repository, https://github.com/okorach/sonar-tools.git
